gentroutils/__init__.py
gentroutils/errors.py
gentroutils/py.typed
gentroutils/transfer.py
gentroutils/io/path/__init__.py
gentroutils/io/path/ftp.py
gentroutils/io/path/gcs.py
gentroutils/io/transfer/__init__.py
gentroutils/io/transfer/ftp_to_gcs.py
gentroutils/io/transfer/model.py
gentroutils/io/transfer/polars_to_gcs.py
gentroutils/parsers/__init__.py
gentroutils/parsers/curation.py
gentroutils/tasks/__init__.py
gentroutils/tasks/crawl.py
gentroutils/tasks/curation.py
gentroutils/tasks/fetch.py
gentroutils-3.1.0.dist-info/METADATA
gentroutils-3.1.0.dist-info/WHEEL
gentroutils-3.1.0.dist-info/entry_points.txt
gentroutils-3.1.0.dist-info/licenses/LICENSE
gentroutils-3.1.0.dist-info/RECORD
