Metadata-Version: 2.4
Name: gentroutils
Version: 3.1.0
Summary: Open Targets python genetics utility CLI tools
Author-email: Szymon Szyszkowski <ss60@sanger.ac.uk>
License-Expression: Apache-2.0
License-File: LICENSE
Classifier: Development Status :: 3 - Alpha
Classifier: Intended Audience :: Healthcare Industry
Classifier: Intended Audience :: Science/Research
Classifier: License :: OSI Approved :: Apache Software License
Classifier: Operating System :: Unix
Classifier: Programming Language :: Python :: 3.13
Classifier: Topic :: Scientific/Engineering :: Bio-Informatics
Requires-Python: >=3.13
Requires-Dist: aioftp>=0.25.1
Requires-Dist: aiohttp>=3.11.18
Requires-Dist: gcsfs>=2025.7.0
Requires-Dist: google-cloud-storage>=3.1.1
Requires-Dist: loguru>=0.7.3
Requires-Dist: opentargets-otter>=25.0.2
Requires-Dist: polars[fsspec]>=1.31.0
Requires-Dist: pydantic>=2.10.6
Requires-Dist: tqdm>=4.67.1
